logger_dsi/__init__.py
logger_dsi/client.py
logger_dsi/config.py
logger_dsi/exceptions.py
loki_client/__init__.py
loki_client/client.py
loki_client/config.py
loki_client/exceptions.py
logger_dsi-0.4.dist-info/METADATA
logger_dsi-0.4.dist-info/WHEEL
logger_dsi-0.4.dist-info/top_level.txt
logger_dsi-0.4.dist-info/RECORD
