Metadata-Version: 2.2
Name: logger_dsi
Version: 0.4
Summary: A Python client library to send logs to DSI's logging system.
Home-page: https://bitbucket.org/dsinno/loggerclient
Author: Design Systems Inno.
Author-email: sebastian@dsinno.io
Classifier: Programming Language :: Python :: 3
Classifier: License :: OSI Approved :: MIT License
Classifier: Operating System :: OS Independent
Requires-Python: >=3.6
Requires-Dist: requests
Dynamic: author
Dynamic: author-email
Dynamic: classifier
Dynamic: description
Dynamic: description-content-type
Dynamic: home-page
Dynamic: requires-dist
Dynamic: requires-python
Dynamic: summary
